flake8_qiskit_migration/__init__.py
flake8_qiskit_migration/command.py
flake8_qiskit_migration/deprecated_paths.py
flake8_qiskit_migration/plugin.py
flake8_qiskit_migration-0.4.0.dist-info/METADATA
flake8_qiskit_migration-0.4.0.dist-info/WHEEL
flake8_qiskit_migration-0.4.0.dist-info/entry_points.txt
flake8_qiskit_migration-0.4.0.dist-info/licenses/LICENSE
flake8_qiskit_migration-0.4.0.dist-info/RECORD
