Metadata-Version: 2.1
Name: flake8-qiskit-migration
Version: 0.4.0
Summary: Quickly detect imports removed in the Qiskit 1.0 release
Project-URL: Homepage, https://github.com/frankharkins/flake8-qiskit-migration
Project-URL: Issues, https://github.com/frankharkins/flake8-qiskit-migration/issues
Author-email: Frank Harkins <frankharkins@hotmail.co.uk>
License-File: LICENSE
Classifier: License :: OSI Approved :: Apache Software License
Classifier: Operating System :: OS Independent
Classifier: Programming Language :: Python :: 3
Requires-Python: >=3.8
Requires-Dist: flake8
